jmbo_calendar
